LICENSE
auth_reports/__init__.py
auth_reports/admin.py
auth_reports/apps.py
auth_reports/static/admin/js/SelectFilter2.js
auth_reports/static/auth_reports/css/select-filter-custom.css
django_auth_reports-2.0.4.dist-info/LICENSE
django_auth_reports-2.0.4.dist-info/WHEEL
django_auth_reports-2.0.4.dist-info/METADATA
django_auth_reports-2.0.4.dist-info/RECORD
